MANIFEST.in
setup.cfg
setup.py
stratus_api/core/__init__.py
stratus_api/core/common.py
stratus_api/core/exceptions.py
stratus_api/core/logs.py
stratus_api/core/requests.py
stratus_api/core/server.py
stratus_api/core/settings.py
stratus_api_core.egg-info/PKG-INFO
stratus_api_core.egg-info/SOURCES.txt
stratus_api_core.egg-info/dependency_links.txt
stratus_api_core.egg-info/requires.txt
stratus_api_core.egg-info/top_level.txt