Metadata-Version: 2.1
Name: stratus-api-core
Version: 0.0.28
Summary: An API stratus_api for simplified development
Home-page: https://bitbucket.org/adarainc/stratus-api-core
Author: adara
Author-email: dot@adara.com
License: UNKNOWN
Platform: UNKNOWN
Classifier: Programming Language :: Python :: 3
Classifier: License :: OSI Approved :: MIT License
Classifier: Operating System :: OS Independent
Requires-Python: >=3.11
